gams/__init__.py
gams/_version.py
gams/connect/__init__.py
gams/connect/connectdatabase.py
gams/connect/connectvalidator.py
gams/connect/errors.py
gams/connect/agents/__init__.py
gams/connect/agents/concatenate.py
gams/connect/agents/connectagent.py
gams/connect/agents/csvreader.py
gams/connect/agents/csvwriter.py
gams/connect/agents/domainwriter.py
gams/connect/agents/excelreader.py
gams/connect/agents/excelwriter.py
gams/connect/agents/filter.py
gams/connect/agents/gamsreader.py
gams/connect/agents/gamswriter.py
gams/connect/agents/gdxreader.py
gams/connect/agents/gdxwriter.py
gams/connect/agents/labelmanipulator.py
gams/connect/agents/projection.py
gams/connect/agents/pythoncode.py
gams/connect/agents/rawcsvreader.py
gams/connect/agents/rawexcelreader.py
gams/connect/agents/sqlreader.py
gams/connect/agents/sqlwriter.py
gams/connect/agents/_excel/__init__.py
gams/connect/agents/_excel/excelagent.py
gams/connect/agents/_excel/workbook.py
gams/connect/agents/_sqlconnectors/__init__.py
gams/connect/agents/_sqlconnectors/_accesshandler.py
gams/connect/agents/_sqlconnectors/_databasehandler.py
gams/connect/agents/_sqlconnectors/_mysqlhandler.py
gams/connect/agents/_sqlconnectors/_postgreshandler.py
gams/connect/agents/_sqlconnectors/_pyodbchandler.py
gams/connect/agents/_sqlconnectors/_sqlalchemyhandler.py
gams/connect/agents/_sqlconnectors/_sqlitehandler.py
gams/connect/agents/_sqlconnectors/_sqlserverhandler.py
gams/connect/agents/schema/CSVReader.yaml
gams/connect/agents/schema/CSVWriter.yaml
gams/connect/agents/schema/Concatenate.yaml
gams/connect/agents/schema/DomainWriter.yaml
gams/connect/agents/schema/ExcelReader.yaml
gams/connect/agents/schema/ExcelWriter.yaml
gams/connect/agents/schema/Filter.yaml
gams/connect/agents/schema/GAMSReader.yaml
gams/connect/agents/schema/GAMSWriter.yaml
gams/connect/agents/schema/GDXReader.yaml
gams/connect/agents/schema/GDXWriter.yaml
gams/connect/agents/schema/LabelManipulator.yaml
gams/connect/agents/schema/Projection.yaml
gamsapi-52.4.0.dist-info/licenses/LICENSE
gamsapi-52.4.0.dist-info/METADATA
gamsapi-52.4.0.dist-info/WHEEL
gamsapi-52.4.0.dist-info/top_level.txt
gamsapi-52.4.0.dist-info/RECORD
